mkdocstrings_handlers/sh/__init__.py
mkdocstrings_handlers/sh/_internal/__init__.py
mkdocstrings_handlers/sh/_internal/config.py
mkdocstrings_handlers/sh/_internal/debug.py
mkdocstrings_handlers/sh/_internal/handler.py
mkdocstrings_handlers/sh/_internal/shdocgen.py
mkdocstrings_handlers/sh/py.typed
mkdocstrings_handlers/sh/templates/material/_base/data.html.jinja
mkdocstrings_handlers/sh/templates/material/data.html.jinja
mkdocstrings_handlers/sh/templates/material/file.html.jinja
mkdocstrings_handlers/sh/templates/material/function.html.jinja
mkdocstrings_handlers/sh/templates/material/lib.jinja
mkdocstrings_handlers/sh/templates/material/section.html.jinja
mkdocstrings_handlers/sh/templates/material/style.css
mkdocstrings_handlers/sh/templates/material/variable.html.jinja
mkdocstrings_sh-0.1.0.dist-info/METADATA
mkdocstrings_sh-0.1.0.dist-info/WHEEL
mkdocstrings_sh-0.1.0.dist-info/entry_points.txt
mkdocstrings_sh-0.1.0.dist-info/licenses/LICENSE
mkdocstrings_sh-0.1.0.dist-info/RECORD
