Metadata-Version: 2.4
Name: mkdocstrings-sh
Version: 0.1.0
Summary: A Sh handler for mkdocstrings.
Author-Email: Kamil Cukrowski <kamilcukrowski@gmail.com>
License-Expression: ISC
License-File: LICENSE
Classifier: Development Status :: 4 - Beta
Classifier: Intended Audience :: Developers
Classifier: Programming Language :: Python
Classifier: Programming Language :: Python :: 3
Classifier: Programming Language :: Python :: 3 :: Only
Classifier: Programming Language :: Python :: 3.9
Classifier: Programming Language :: Python :: 3.10
Classifier: Programming Language :: Python :: 3.11
Classifier: Programming Language :: Python :: 3.12
Classifier: Programming Language :: Python :: 3.13
Classifier: Programming Language :: Python :: 3.14
Classifier: Topic :: Documentation
Classifier: Topic :: Software Development
Classifier: Topic :: Utilities
Classifier: Typing :: Typed
Project-URL: Homepage, https://kamilcuk.github.io/mkdocstrings-sh
Project-URL: Documentation, https://kamilcuk.github.io/mkdocstrings-sh
Project-URL: Changelog, https://kamilcuk.github.io/mkdocstrings-sh/changelog
Project-URL: Repository, https://github.com/kamilcuk/mkdocstrings-sh
Project-URL: Issues, https://github.com/kamilcuk/mkdocstrings-sh/issues
Project-URL: Discussions, https://github.com/kamilcuk/mkdocstrings-sh/discussions
Project-URL: Gitter, https://gitter.im/mkdocstrings-sh/community
Project-URL: Funding, https://github.com/sponsors/kamilcuk
Requires-Python: >=3.9
Requires-Dist: mkdocstrings>=0.18
